{
  "BTCUSDT": 63178.1,
  "ETHUSDT": 1820.53,
  "SOLUSDT": 76.74,
  "XRPUSDT": 1.3317,
  "BNBUSDT": 587.45,
  "DOGEUSDT": 0.0913,
  "XAGUSDT": 87.99,
  "BCHUSDT": 478.53,
  "XAUUSDT": 5174.85,
  "HYPEUSDT": 26.463,
  "PAXGUSDT": 5188.15,
  "WLFIUSDT": 0.1074,
  "ZECUSDT": 234.34,
  "TRXUSDT": 0.27998,
  "SUIUSDT": 0.8565,
  "ASTERUSDT": 0.6822,
  "PIPPINUSDT": 0.72982,
  "ADAUSDT": 0.2573,
  "AVAXUSDT": 8.29,
  "UNIUSDT": 3.303,
  "LINKUSDT": 8.163,
  "LTCUSDT": 50.63,
  "1000PEPEUSDT": 0.0038976,
  "PUMPUSDT": 0.001743,
  "ENAUSDT": 0.0952,
  "KITEUSDT": 0.24732,
  "NEARUSDT": 0.971,
  "ARCUSDT": 0.09496,
  "WLDUSDT": 0.3678,
  "AAVEUSDT": 113.18,
  "LITUSDT": 1.368,
  "FILUSDT": 0.874,
  "TRUMPUSDT": 3.264,
  "DOTUSDT": 1.245,
  "TAOUSDT": 165.64,
  "XPLUSDT": 0.0853,
  "ENSOUSDT": 2.1461,
  "ESPUSDT": 0.17331,
  "TONUSDT": 1.3231,
  "ATOMUSDT": 2.036,
  "BERAUSDT": 0.5889,
  "ZROUSDT": 1.4943,
  "APTUSDT": 0.8109,
  "HBARUSDT": 0.09326,
  "1000SHIBUSDT": 0.005924,
  "XLMUSDT": 0.14946,
  "RIVERUSDT": 8.874,
  "ARBUSDT": 0.0915,
  "ICPUSDT": 2.058,
  "AXSUSDT": 1.199,
  "XMRUSDT": 324.61,
  "OPUSDT": 0.1175,
  "MONUSDT": 0.02,
  "CRVUSDT": 0.219,
  "FFUSDT": 0.07735,
  "WIFUSDT": 0.1976,
  "PENGUUSDT": 0.006281,
  "BARDUSDT": 0.7615,
  "FETUSDT": 0.1514,
  "ETCUSDT": 8.16,
  "POWERUSDT": 0.58891,
  "POLUSDT": 0.10559,
  "1000BONKUSDT": 0.005758,
  "IPUSDT": 1.004,
  "BANUSDT": 0.12315,
  "PARTIUSDT": 0.09701,
  "HUSDT": 0.13179,
  "FARTCOINUSDT": 0.1411,
  "BTCDOMUSDT": 5116.1,
  "INJUSDT": 3.165,
  "CHZUSDT": 0.03403,
  "SENTUSDT": 0.0229,
  "ETHFIUSDT": 0.4455,
  "VIRTUALUSDT": 0.5783,
  "ONDOUSDT": 0.2429,
  "DASHUSDT": 31.74,
  "TIAUSDT": 0.2944,
  "\u5e01\u5b89\u4eba\u751fUSDT": 0.05836,
  "0GUSDT": 0.6167,
  "SEIUSDT": 0.065,
  "ZKUSDT": 0.01885,
  "ZAMAUSDT": 0.02273,
  "SIRENUSDT": 0.2846,
  "STABLEUSDT": 0.029508,
  "LYNUSDT": 0.31404,
  "JUPUSDT": 0.1413,
  "ALCHUSDT": 0.07799,
  "CCUSDT": 0.15907,
  "KAITOUSDT": 0.2903,
  "LDOUSDT": 0.2948,
  "PENDLEUSDT": 1.1797,
  "BULLAUSDT": 0.04183,
  "HOMEUSDT": 0.03013,
  "RENDERUSDT": 1.344,
  "BANANAS31USDT": 0.004734,
  "QUSDT": 0.021272,
  "1000RATSUSDT": 0.04371,
  "UBUSDT": 0.04123,
  "NIGHTUSDT": 0.05741,
  "BIOUSDT": 0.02435,
  "SKRUSDT": 0.024461,
  "SKYAIUSDT": 0.03853,
  "ATUSDT": 0.15978,
  "STRKUSDT": 0.04047,
  "BTRUSDT": 0.1913,
  "ZENUSDT": 5.278,
  "CAKEUSDT": 1.1913,
  "OPNUSDT": 0.4963,
  "DUSKUSDT": 0.07734,
  "AZTECUSDT": 0.02382,
  "MYXUSDT": 0.477,
  "ALGOUSDT": 0.0834,
  "SANDUSDT": 0.07763,
  "VVVUSDT": 3.284,
  "HANAUSDT": 0.03341,
  "MUSDT": 1.392,
  "PIEVERSEUSDT": 0.4278,
  "MORPHOUSDT": 1.5682,
  "GPSUSDT": 0.01161,
  "TRADOORUSDT": 1.492,
  "USDCUSDT": 0.99965,
  "GALAUSDT": 0.00344,
  "GUNUSDT": 0.02763,
  "APEUSDT": 0.1017,
  "ZILUSDT": 0.004,
  "LAUSDT": 0.2085,
  "JTOUSDT": 0.2746,
  "GUAUSDT": 0.1721,
  "SKYUSDT": 0.06332,
  "RAVEUSDT": 0.30264,
  "FOGOUSDT": 0.02805,
  "B2USDT": 0.7605,
  "ROSEUSDT": 0.0119,
  "STEEMUSDT": 0.05721,
  "ORCAUSDT": 0.925,
  "ALLOUSDT": 0.09219,
  "XPINUSDT": 0.001562,
  "AGLDUSDT": 0.2756,
  "METUSDT": 0.1698,
  "GIGGLEUSDT": 24.65,
  "TSLAUSDT": 397.16,
  "BEAMXUSDT": 0.001897,
  "BUSDT": 0.1315,
  "EIGENUSDT": 0.1807,
  "JELLYJELLYUSDT": 0.06183,
  "\u6211\u8e0f\u9a6c\u6765\u4e86USDT": 0.011554,
  "HUMAUSDT": 0.01171,
  "SYRUPUSDT": 0.19527,
  "MSTRUSDT": 122.38,
  "PYTHUSDT": 0.04963,
  "SNXUSDT": 0.347,
  "AEROUSDT": 0.3082,
  "COLLECTUSDT": 0.04581,
  "ESPORTSUSDT": 0.34279,
  "AWEUSDT": 0.0507,
  "VETUSDT": 0.007149,
  "LPTUSDT": 2.207,
  "AVNTUSDT": 0.1701,
  "ORDIUSDT": 2.3,
  "TRIAUSDT": 0.01954,
  "XTZUSDT": 0.368,
  "NEOUSDT": 2.615,
  "ZKPUSDT": 0.08398,
  "DYDXUSDT": 0.087,
  "DEXEUSDT": 3.379,
  "NXPCUSDT": 0.2558,
  "MOVEUSDT": 0.0208,
  "FORMUSDT": 0.1887,
  "RESOLVUSDT": 0.06672,
  "SUSDT": 0.03894,
  "CYSUSDT": 0.373,
  "MEUSDT": 0.1151,
  "PNUTUSDT": 0.04303,
  "AUCTIONUSDT": 4.745,
  "COMPUSDT": 17.13,
  "CYBERUSDT": 0.5291,
  "GWEIUSDT": 0.030898,
  "ENSUSDT": 5.92,
  "SOMIUSDT": 0.1925,
  "STGUSDT": 0.1301,
  "1000LUNCUSDT": 0.03488,
  "STXUSDT": 0.2309,
  "1000FLOKIUSDT": 0.02769,
  "BEATUSDT": 0.2158,
  "LINEAUSDT": 0.003186,
  "VANAUSDT": 1.379,
  "WUSDT": 0.01813,
  "YGGUSDT": 0.0401,
  "UAIUSDT": 0.2464,
  "TRBUSDT": 13.85,
  "NAORISUSDT": 0.03581,
  "SPACEUSDT": 0.009023,
  "PLUMEUSDT": 0.00894,
  "AGTUSDT": 0.00557,
  "JASMYUSDT": 0.005552,
  "EDUUSDT": 0.1188,
  "INITUSDT": 0.08185,
  "CLOUSDT": 0.08989,
  "BANKUSDT": 0.03851,
  "TAUSDT": 0.04043,
  "EULUSDT": 0.927,
  "MERLUSDT": 0.04474,
  "SPXUSDT": 0.2728,
  "JSTUSDT": 0.045838,
  "USELESSUSDT": 0.03666,
  "MANAUSDT": 0.0896,
  "NMRUSDT": 7.615,
  "2ZUSDT": 0.06619,
  "ARUSDT": 1.833,
  "ATHUSDT": 0.00488,
  "GRTUSDT": 0.0256,
  "TAGUSDT": 0.000382,
  "BIRBUSDT": 0.15288,
  "WCTUSDT": 0.056,
  "IMXUSDT": 0.1525,
  "API3USDT": 0.2788,
  "CFXUSDT": 0.04776,
  "OGUSDT": 2.936,
  "MMTUSDT": 0.1181,
  "MOODENGUSDT": 0.05004,
  "QNTUSDT": 62.88,
  "FLOWUSDT": 0.035,
  "COWUSDT": 0.2159,
  "IOTAUSDT": 0.0653,
  "SPKUSDT": 0.01992,
  "ZORAUSDT": 0.01877,
  "COAIUSDT": 0.2963,
  "ZRXUSDT": 0.1017,
  "1INCHUSDT": 0.0862,
  "LRCUSDT": 0.03225,
  "SFPUSDT": 0.2496,
  "LIGHTUSDT": 0.2194,
  "LUNA2USDT": 0.06095,
  "KAIAUSDT": 0.05219,
  "THETAUSDT": 0.1833,
  "FIGHTUSDT": 0.007208,
  "ARKMUSDT": 0.1027,
  "RUNEUSDT": 0.3838,
  "PTBUSDT": 0.001213,
  "UMAUSDT": 0.4583,
  "IOUSDT": 0.1073,
  "FHEUSDT": 0.028,
  "4USDT": 0.00756,
  "IDOLUSDT": 0.02299,
  "YFIUSDT": 2632.0,
  "SIGNUSDT": 0.023,
  "NEIROUSDT": 6.52e-05,
  "BREVUSDT": 0.1291,
  "AXLUSDT": 0.05016,
  "TNSRUSDT": 0.04832,
  "GASUSDT": 1.505,
  "EGLDUSDT": 4.197,
  "AKEUSDT": 0.0002964,
  "XNYUSDT": 0.005188,
  "KGENUSDT": 0.17752,
  "SAHARAUSDT": 0.01423,
  "RPLUSDT": 1.973,
  "GMTUSDT": 0.01087,
  "KASUSDT": 0.02922,
  "ANIMEUSDT": 0.004589,
  "BLUAIUSDT": 0.005091,
  "VELVETUSDT": 0.08467,
  "PROVEUSDT": 0.274,
  "AIAUSDT": 0.08339,
  "TWTUSDT": 0.4924,
  "BOMEUSDT": 0.0003703,
  "ACTUSDT": 0.01345,
  "SXTUSDT": 0.02397,
  "AIOUSDT": 0.07618,
  "XPTUSDT": 2167.27,
  "MINAUSDT": 0.05693,
  "TSTUSDT": 0.00946,
  "PEOPLEUSDT": 0.00618,
  "AUSDT": 0.0766,
  "OPENUSDT": 0.143,
  "MAGICUSDT": 0.06286,
  "MEGAUSDT": 0.1288,
  "NOMUSDT": 0.004384,
  "FOLKSUSDT": 1.138,
  "AVAAIUSDT": 0.00696,
  "YBUSDT": 0.1552,
  "SUSHIUSDT": 0.19,
  "BATUSDT": 0.1146,
  "GRASSUSDT": 0.17,
  "STOUSDT": 0.05754,
  "POPCATUSDT": 0.04549,
  "KERNELUSDT": 0.07319,
  "MANTAUSDT": 0.06344,
  "CATIUSDT": 0.03688,
  "BSVUSDT": 14.84,
  "TUTUSDT": 0.00971,
  "STORJUSDT": 0.0909,
  "TURBOUSDT": 0.0009558,
  "ZBTUSDT": 0.06799,
  "SOPHUSDT": 0.008406,
  "AINUSDT": 0.04024,
  "SUPERUSDT": 0.106,
  "ACHUSDT": 0.006911,
  "FUSDT": 0.005413,
  "ZKCUSDT": 0.0804,
  "BABYUSDT": 0.01183,
  "ICNTUSDT": 0.3985,
  "GLMUSDT": 0.14948,
  "SWARMSUSDT": 0.00611,
  "BLURUSDT": 0.01901,
  "TAKEUSDT": 0.02254,
  "LAYERUSDT": 0.0797,
  "VELODROMEUSDT": 0.01354,
  "SAPIENUSDT": 0.08593,
  "NILUSDT": 0.04678,
  "KSMUSDT": 4.529,
  "ARPAUSDT": 0.00935,
  "DAMUSDT": 0.02167,
  "MASKUSDT": 0.4036,
  "XVGUSDT": 0.005735,
  "ONTUSDT": 0.0396,
  "SOONUSDT": 0.1561,
  "ASRUSDT": 1.337,
  "AIXBTUSDT": 0.01805,
  "TRUTHUSDT": 0.009697,
  "CVXUSDT": 1.72,
  "RAREUSDT": 0.01862,
  "SONICUSDT": 0.04417,
  "SOLVUSDT": 0.00419,
  "INUSDT": 0.06508,
  "BELUSDT": 0.0958,
  "EDENUSDT": 0.03181,
  "CTSIUSDT": 0.0241,
  "RAYSOLUSDT": 0.5773,
  "ALTUSDT": 0.00723,
  "ANKRUSDT": 0.00414,
  "SANTOSUSDT": 1.58,
  "MUBARAKUSDT": 0.01357,
  "SUNUSDT": 0.016327,
  "MEMEUSDT": 0.0006393,
  "C98USDT": 0.0242,
  "PROMPTUSDT": 0.04376,
  "THEUSDT": 0.2417,
  "DRIFTUSDT": 0.0783,
  "CELOUSDT": 0.073,
  "CRCLUSDT": 60.58,
  "AKTUSDT": 0.2935,
  "ERAUSDT": 0.1398,
  "DEGOUSDT": 0.3125,
  "MELANIAUSDT": 0.1075,
  "FRAXUSDT": 0.623,
  "KMNOUSDT": 0.02354,
  "ARIAUSDT": 0.07216,
  "IDUSDT": 0.04267,
  "POLYXUSDT": 0.0403,
  "WETUSDT": 0.08084,
  "KOMAUSDT": 0.00722,
  "FLOCKUSDT": 0.06212,
  "KAVAUSDT": 0.046,
  "PROMUSDT": 1.228,
  "WALUSDT": 0.0717,
  "HYPERUSDT": 0.0884,
  "DYMUSDT": 0.03793,
  "RSRUSDT": 0.001346,
  "QTUMUSDT": 0.86,
  "BASUSDT": 0.005493,
  "GMXUSDT": 6.196,
  "ELSAUSDT": 0.07839,
  "ZEREBROUSDT": 0.0065,
  "IOTXUSDT": 0.00465,
  "VTHOUSDT": 0.0005887,
  "TUSDT": 0.006315,
  "COTIUSDT": 0.01106,
  "ENJUSDT": 0.01837,
  "LSKUSDT": 0.1319,
  "NEWTUSDT": 0.06281,
  "ONUSDT": 0.08174,
  "SKLUSDT": 0.00635,
  "BANANAUSDT": 4.056,
  "BIGTIMEUSDT": 0.01398,
  "ASTRUSDT": 0.006963,
  "NOTUSDT": 0.0003528,
  "WOOUSDT": 0.01549,
  "ACEUSDT": 0.1467,
  "SAGAUSDT": 0.02904,
  "AEVOUSDT": 0.02343,
  "1000SATSUSDT": 1.04e-05,
  "FIDAUSDT": 0.01546,
  "OGNUSDT": 0.0214,
  "BROCCOLI714USDT": 0.01238,
  "CROSSUSDT": 0.09765,
  "RDNTUSDT": 0.005026,
  "STBLUSDT": 0.03298,
  "IRUSDT": 0.07306,
  "LISTAUSDT": 0.079,
  "ONEUSDT": 0.00223,
  "HOLOUSDT": 0.05226,
  "HMSTRUSDT": 0.0001617,
  "HIPPOUSDT": 0.0005716,
  "RVNUSDT": 0.00561,
  "USUALUSDT": 0.01258,
  "BANDUSDT": 0.2013,
  "MIRAUSDT": 0.0774,
  "GUSDT": 0.003371,
  "SPORTFUNUSDT": 0.04404,
  "KNCUSDT": 0.1295,
  "SYNUSDT": 0.04605,
  "METISUSDT": 3.163,
  "DOGSUSDT": 2.59e-05,
  "LQTYUSDT": 0.2673,
  "DOLOUSDT": 0.03707,
  "RLCUSDT": 0.3863,
  "AMZNUSDT": 205.65,
  "CVCUSDT": 0.03095,
  "CUSDT": 0.05206,
  "APRUSDT": 0.08698,
  "PLAYUSDT": 0.01703,
  "TRUUSDT": 0.005029,
  "DEEPUSDT": 0.02414,
  "HAEDALUSDT": 0.02619,
  "CHRUSDT": 0.0185,
  "BBUSDT": 0.02556,
  "HEMIUSDT": 0.00895,
  "RONINUSDT": 0.0956,
  "HEIUSDT": 0.0778,
  "SSVUSDT": 2.851,
  "ALLINDEXUSDT": 0.4433,
  "MAVUSDT": 0.01376,
  "1MBABYDOGEUSDT": 0.0003623,
  "NTRNUSDT": 0.01179,
  "TACUSDT": 0.003944,
  "XPDUSDT": 1757.19,
  "HFTUSDT": 0.01414,
  "XVSUSDT": 2.841,
  "ALICEUSDT": 0.098,
  "CKBUSDT": 0.001474,
  "RIFUSDT": 0.03552,
  "FUNUSDT": 0.001358,
  "TREEUSDT": 0.0671,
  "FLUIDUSDT": 1.907,
  "ACXUSDT": 0.03223,
  "GTCUSDT": 0.084,
  "IRYSUSDT": 0.02084,
  "DENTUSDT": 0.000122,
  "CLANKERUSDT": 29.17,
  "MITOUSDT": 0.0375,
  "TURTLEUSDT": 0.03875,
  "VANRYUSDT": 0.005236,
  "ICXUSDT": 0.0352,
  "VINEUSDT": 0.01638,
  "EVAAUSDT": 0.4586,
  "GRIFFAINUSDT": 0.0076,
  "NFPUSDT": 0.01432,
  "LABUSDT": 0.13199,
  "PUNDIXUSDT": 0.1563,
  "ALPINEUSDT": 0.4109,
  "MOVRUSDT": 1.228,
  "SCRUSDT": 0.04019,
  "MEWUSDT": 0.0005611,
  "HOTUSDT": 0.000354,
  "IOSTUSDT": 0.001137,
  "JCTUSDT": 0.001647,
  "EPICUSDT": 0.2658,
  "REDUSDT": 0.1525,
  "AIOTUSDT": 0.02307,
  "REZUSDT": 0.002761,
  "COOKIEUSDT": 0.01609,
  "FIOUSDT": 0.00791,
  "BLESSUSDT": 0.004761,
  "SHELLUSDT": 0.0279,
  "ARKUSDT": 0.1735,
  "A2ZUSDT": 0.000807,
  "CARVUSDT": 0.05578,
  "GOATUSDT": 0.01869,
  "BNTUSDT": 0.2683,
  "RECALLUSDT": 0.05275,
  "MLNUSDT": 3.219,
  "ZETAUSDT": 0.04898,
  "SPELLUSDT": 0.0001735,
  "1000CHEEMSUSDT": 0.0004375,
  "USTCUSDT": 0.004689,
  "HOOKUSDT": 0.02245,
  "PHBUSDT": 0.1376,
  "INXUSDT": 0.011347,
  "BRETTUSDT": 0.0067,
  "1000WHYUSDT": 9.9e-06,
  "CETUSUSDT": 0.01504,
  "WAXPUSDT": 0.006208,
  "TOSHIUSDT": 0.000195,
  "BICOUSDT": 0.02082,
  "XAIUSDT": 0.00914,
  "TOWNSUSDT": 0.003293,
  "SAFEUSDT": 0.0988,
  "BROCCOLIF3BUSDT": 0.003351,
  "ILVUSDT": 3.463,
  "HIVEUSDT": 0.06303,
  "PORTALUSDT": 0.01203,
  "ACUUSDT": 0.10307,
  "MOCAUSDT": 0.01552,
  "AIUSDT": 0.02033,
  "VICUSDT": 0.04417,
  "HIGHUSDT": 0.1384,
  "1000CATUSDT": 0.001618,
  "BDXNUSDT": 0.00914,
  "CHILLGUYUSDT": 0.0097,
  "INTCUSDT": 44.27,
  "TRUSTUSDT": 0.071,
  "FORTHUSDT": 0.971,
  "ATAUSDT": 0.0112,
  "POWRUSDT": 0.06079,
  "ORDERUSDT": 0.05148,
  "DUSDT": 0.0068,
  "1000XECUSDT": 0.00739,
  "MTLUSDT": 0.2569,
  "SCRTUSDT": 0.0776,
  "ONGUSDT": 0.06086,
  "CELRUSDT": 0.00233,
  "DOODUSDT": 0.003202,
  "BMTUSDT": 0.01502,
  "JOEUSDT": 0.03341,
  "AVAUSDT": 0.1965,
  "XANUSDT": 0.00723,
  "PIXELUSDT": 0.004816,
  "DIAUSDT": 0.1771,
  "PHAUSDT": 0.02223,
  "BOBUSDT": 0.005522,
  "SLPUSDT": 0.0005788,
  "RLSUSDT": 0.004928,
  "FLUXUSDT": 0.061,
  "CGPTUSDT": 0.01868,
  "LUMIAUSDT": 0.05669,
  "SYSUSDT": 0.01059,
  "TLMUSDT": 0.001544,
  "COSUSDT": 0.000959,
  "USUSDT": 0.00339,
  "OXTUSDT": 0.01606,
  "CTKUSDT": 0.2279,
  "DODOXUSDT": 0.01431,
  "AERGOUSDT": 0.05295,
  "HOODUSDT": 71.18,
  "MBOXUSDT": 0.01811,
  "MAVIAUSDT": 0.02879,
  "PUMPBTCUSDT": 0.01495,
  "SQDUSDT": 0.03683,
  "PUFFERUSDT": 0.02869,
  "B3USDT": 0.0003788,
  "ZKJUSDT": 0.02103,
  "BRUSDT": 0.05468,
  "ETHWUSDT": 0.2981,
  "TAIKOUSDT": 0.1163,
  "1000000MOGUSDT": 0.1557,
  "1000000BOBUSDT": 0.01131,
  "VFYUSDT": 0.01556,
  "OLUSDT": 0.01109,
  "COINUSDT": 157.69,
  "DEGENUSDT": 0.000611,
  "MAGMAUSDT": 0.10094,
  "PLTRUSDT": 128.51
}