{
  "BTCUSDT": 71481.6,
  "ETHUSDT": 2079.63,
  "SOLUSDT": 90.45,
  "XRPUSDT": 1.4073,
  "BNBUSDT": 652.8,
  "DOGEUSDT": 0.09283,
  "XAUUSDT": 5187.55,
  "PAXGUSDT": 5199.59,
  "BCHUSDT": 457.08,
  "HYPEUSDT": 32.383,
  "XAGUSDT": 85.74,
  "WLFIUSDT": 0.1066,
  "ZECUSDT": 226.86,
  "TRXUSDT": 0.28348,
  "UNIUSDT": 4.018,
  "SUIUSDT": 0.9393,
  "ADAUSDT": 0.2711,
  "ASTERUSDT": 0.7089,
  "1000PEPEUSDT": 0.0035367,
  "LINKUSDT": 9.203,
  "AVAXUSDT": 9.358,
  "LTCUSDT": 56.1,
  "NEARUSDT": 1.38,
  "PUMPUSDT": 0.002024,
  "ENAUSDT": 0.1173,
  "AAVEUSDT": 114.84,
  "DOTUSDT": 1.545,
  "WLDUSDT": 0.4044,
  "XPLUSDT": 0.1168,
  "FILUSDT": 1.018,
  "TAOUSDT": 192.02,
  "1000SHIBUSDT": 0.005556,
  "LITUSDT": 1.311,
  "RIVERUSDT": 17.764,
  "TRUMPUSDT": 3.406,
  "PIPPINUSDT": 0.32931,
  "KITEUSDT": 0.23146,
  "ZROUSDT": 1.8624,
  "APTUSDT": 1.0025,
  "TONUSDT": 1.2981,
  "HBARUSDT": 0.10118,
  "ATOMUSDT": 1.878,
  "HUSDT": 0.12484,
  "XMRUSDT": 349.86,
  "XLMUSDT": 0.15504,
  "ARBUSDT": 0.1041,
  "ICPUSDT": 2.589,
  "CRVUSDT": 0.261,
  "WIFUSDT": 0.2094,
  "BERAUSDT": 0.5504,
  "MONUSDT": 0.02149,
  "VIRTUALUSDT": 0.7641,
  "FETUSDT": 0.1529,
  "PENGUUSDT": 0.007177,
  "AXSUSDT": 1.217,
  "OPUSDT": 0.1293,
  "FFUSDT": 0.07365,
  "CCUSDT": 0.15639,
  "ETCUSDT": 8.64,
  "BARDUSDT": 1.0827,
  "ARCUSDT": 0.03565,
  "VVVUSDT": 6.052,
  "POLUSDT": 0.10298,
  "SAHARAUSDT": 0.02935,
  "ONDOUSDT": 0.2677,
  "BTCDOMUSDT": 5228.2,
  "FORMUSDT": 0.3673,
  "ETHFIUSDT": 0.535,
  "1000BONKUSDT": 0.006134,
  "DASHUSDT": 34.98,
  "PARTIUSDT": 0.08481,
  "POWERUSDT": 0.18391,
  "FARTCOINUSDT": 0.169,
  "IPUSDT": 0.85,
  "TIAUSDT": 0.3402,
  "\u5e01\u5b89\u4eba\u751fUSDT": 0.06332,
  "SIRENUSDT": 0.37227,
  "CHZUSDT": 0.03684,
  "SEIUSDT": 0.06868,
  "BANUSDT": 0.10205,
  "SENTUSDT": 0.02107,
  "ENSOUSDT": 1.2996,
  "JUPUSDT": 0.187,
  "1000RATSUSDT": 0.05429,
  "INJUSDT": 3.087,
  "ESPUSDT": 0.12159,
  "STABLEUSDT": 0.030876,
  "KAITOUSDT": 0.3676,
  "0GUSDT": 0.6177,
  "BANANAS31USDT": 0.005384,
  "BUSDT": 0.2162,
  "SKYAIUSDT": 0.04794,
  "LDOUSDT": 0.3128,
  "RENDERUSDT": 1.391,
  "PENDLEUSDT": 1.2972,
  "GUAUSDT": 0.24061,
  "ALCHUSDT": 0.07898,
  "ZKUSDT": 0.01888,
  "ZAMAUSDT": 0.01977,
  "MORPHOUSDT": 1.9425,
  "CRCLUSDT": 105.6,
  "GIGGLEUSDT": 31.49,
  "PHAUSDT": 0.04139,
  "QUSDT": 0.025239,
  "JELLYJELLYUSDT": 0.08301,
  "ATUSDT": 0.15775,
  "GWEIUSDT": 0.042099,
  "BIOUSDT": 0.02136,
  "HOMEUSDT": 0.029256,
  "PIEVERSEUSDT": 0.5215,
  "SIGNUSDT": 0.02845,
  "CAKEUSDT": 1.4003,
  "BULLAUSDT": 0.02603,
  "ZENUSDT": 5.711,
  "SANDUSDT": 0.08588,
  "ROBOUSDT": 0.04653,
  "NIGHTUSDT": 0.06181,
  "GALAUSDT": 0.00363,
  "STRKUSDT": 0.04081,
  "SKYUSDT": 0.073,
  "LYNUSDT": 0.29807,
  "TSLAUSDT": 397.53,
  "ALLOUSDT": 0.1116,
  "MSTRUSDT": 143.09,
  "MUSDT": 1.3889,
  "BTRUSDT": 0.18634,
  "ALGOUSDT": 0.0882,
  "HANAUSDT": 0.03485,
  "AEROUSDT": 0.3655,
  "STGUSDT": 0.1652,
  "MYXUSDT": 0.302,
  "EIGENUSDT": 0.1934,
  "APEUSDT": 0.1033,
  "GPSUSDT": 0.009239,
  "OPNUSDT": 0.4852,
  "GUNUSDT": 0.02145,
  "USDCUSDT": 0.99942,
  "TRADOORUSDT": 1.465,
  "DUSKUSDT": 0.08825,
  "SYRUPUSDT": 0.23646,
  "AZTECUSDT": 0.02249,
  "HUMAUSDT": 0.012864,
  "XPINUSDT": 0.001394,
  "BEAMXUSDT": 0.001947,
  "UBUSDT": 0.03545,
  "B2USDT": 0.7095,
  "NEOUSDT": 2.611,
  "ATHUSDT": 0.006126,
  "JTOUSDT": 0.2755,
  "ZILUSDT": 0.00414,
  "PYTHUSDT": 0.05034,
  "ORDIUSDT": 2.533,
  "1000LUNCUSDT": 0.04363,
  "XTZUSDT": 0.38,
  "METUSDT": 0.1762,
  "VETUSDT": 0.007339,
  "DYDXUSDT": 0.097,
  "ROSEUSDT": 0.01217,
  "TAUSDT": 0.04893,
  "AVNTUSDT": 0.1719,
  "BEATUSDT": 0.2743,
  "MOVEUSDT": 0.02246,
  "LAUSDT": 0.2127,
  "COMPUSDT": 18.11,
  "AIXBTUSDT": 0.02961,
  "\u6211\u8e0f\u9a6c\u6765\u4e86USDT": 0.010998,
  "NXPCUSDT": 0.2735,
  "LINEAUSDT": 0.003264,
  "FOGOUSDT": 0.02297,
  "PNUTUSDT": 0.04734,
  "COLLECTUSDT": 0.04262,
  "SUSDT": 0.04212,
  "ESPORTSUSDT": 0.30412,
  "SPXUSDT": 0.3507,
  "ENSUSDT": 6.122,
  "1000FLOKIUSDT": 0.02883,
  "SNXUSDT": 0.338,
  "KAVAUSDT": 0.0587,
  "ZKPUSDT": 0.08852,
  "4USDT": 0.0099,
  "GRASSUSDT": 0.2941,
  "SKRUSDT": 0.023175,
  "TRBUSDT": 14.839,
  "TAGUSDT": 0.0004121,
  "AGLDUSDT": 0.2241,
  "AUCTIONUSDT": 4.757,
  "WETUSDT": 0.11868,
  "ORCAUSDT": 0.884,
  "LPTUSDT": 2.332,
  "USELESSUSDT": 0.04679,
  "ARUSDT": 1.667,
  "EULUSDT": 1.155,
  "STXUSDT": 0.2646,
  "PLUMEUSDT": 0.00953,
  "RAVEUSDT": 0.34098,
  "JASMYUSDT": 0.005671,
  "DENTUSDT": 0.000266,
  "WUSDT": 0.01902,
  "MANAUSDT": 0.098,
  "MEUSDT": 0.1146,
  "JSTUSDT": 0.0482,
  "SOMIUSDT": 0.1984,
  "TRIAUSDT": 0.01742,
  "IOTAUSDT": 0.0678,
  "BANKUSDT": 0.03639,
  "AGTUSDT": 0.005724,
  "CYBERUSDT": 0.5467,
  "GRTUSDT": 0.02649,
  "DEXEUSDT": 3.503,
  "CFXUSDT": 0.04966,
  "RESOLVUSDT": 0.05934,
  "IMXUSDT": 0.1614,
  "MOODENGUSDT": 0.05029,
  "COAIUSDT": 0.3207,
  "YGGUSDT": 0.03963,
  "WCTUSDT": 0.05978,
  "EDUUSDT": 0.1039,
  "FLOWUSDT": 0.0348,
  "PTBUSDT": 0.0012,
  "API3USDT": 0.285,
  "QNTUSDT": 63.73,
  "SFPUSDT": 0.2772,
  "CYSUSDT": 0.3072,
  "MANTRAUSDT": 0.01875,
  "MEMEUSDT": 0.0006316,
  "AWEUSDT": 0.05103,
  "NMRUSDT": 7.646,
  "MERLUSDT": 0.04168,
  "SPKUSDT": 0.02011,
  "RUNEUSDT": 0.4242,
  "2ZUSDT": 0.0733,
  "MMTUSDT": 0.1167,
  "AXLUSDT": 0.05424,
  "1INCHUSDT": 0.0974,
  "LIGHTUSDT": 0.1879,
  "PEOPLEUSDT": 0.00699,
  "KGENUSDT": 0.2116,
  "LAYERUSDT": 0.0869,
  "INITUSDT": 0.08131,
  "NEIROUSDT": 7.053e-05,
  "CLOUSDT": 0.07203,
  "THETAUSDT": 0.1957,
  "NAORISUSDT": 0.03109,
  "ARKMUSDT": 0.1095,
  "BREVUSDT": 0.1447,
  "SPACEUSDT": 0.007538,
  "MUBARAKUSDT": 0.0156,
  "ZRXUSDT": 0.1038,
  "EGLDUSDT": 4.226,
  "ZORAUSDT": 0.01742,
  "VANAUSDT": 1.45,
  "KASUSDT": 0.03091,
  "USUALUSDT": 0.01581,
  "KAIAUSDT": 0.05456,
  "FOLKSUSDT": 1.182,
  "BIRBUSDT": 0.14361,
  "IOUSDT": 0.1143,
  "COWUSDT": 0.2304,
  "POPCATUSDT": 0.04975,
  "SUNUSDT": 0.015899,
  "SOPHUSDT": 0.008615,
  "AKEUSDT": 0.0002471,
  "SWARMSUSDT": 0.007441,
  "LRCUSDT": 0.03106,
  "TSTUSDT": 0.01005,
  "YFIUSDT": 2693.0,
  "GMTUSDT": 0.01153,
  "AVAAIUSDT": 0.007884,
  "BOMEUSDT": 0.0004143,
  "VELVETUSDT": 0.08721,
  "AIAUSDT": 0.08588,
  "ANIMEUSDT": 0.004744,
  "PROVEUSDT": 0.2823,
  "TWTUSDT": 0.5019,
  "AUSDT": 0.0787,
  "SUSHIUSDT": 0.2088,
  "MEGAUSDT": 0.13229,
  "TURBOUSDT": 0.0009966,
  "KNCUSDT": 0.1415,
  "STEEMUSDT": 0.05674,
  "MIRAUSDT": 0.0896,
  "ACTUSDT": 0.01395,
  "LUNA2USDT": 0.06454,
  "BATUSDT": 0.1053,
  "NILUSDT": 0.051,
  "VELODROMEUSDT": 0.01618,
  "AIOUSDT": 0.07985,
  "OPENUSDT": 0.1451,
  "GASUSDT": 1.613,
  "CATIUSDT": 0.03992,
  "STOUSDT": 0.05939,
  "AKTUSDT": 0.3398,
  "OGUSDT": 2.826,
  "MANTAUSDT": 0.0658,
  "HIPPOUSDT": 0.0007556,
  "TUTUSDT": 0.01068,
  "BSVUSDT": 15.19,
  "BLUAIUSDT": 0.00436,
  "ALICEUSDT": 0.133,
  "BABYUSDT": 0.01146,
  "XNYUSDT": 0.006291,
  "FHEUSDT": 0.02741,
  "SUPERUSDT": 0.1184,
  "SOONUSDT": 0.1632,
  "TNSRUSDT": 0.04534,
  "FIOUSDT": 0.00996,
  "KMNOUSDT": 0.02451,
  "KSMUSDT": 4.713,
  "ZBTUSDT": 0.07298,
  "DAMUSDT": 0.02736,
  "MINAUSDT": 0.0576,
  "MAGICUSDT": 0.06181,
  "XVGUSDT": 0.005572,
  "UMAUSDT": 0.442,
  "KERNELUSDT": 0.07636,
  "FUSDT": 0.005567,
  "SAPIENUSDT": 0.08433,
  "MASKUSDT": 0.4423,
  "RPLUSDT": 1.965,
  "ASRUSDT": 1.326,
  "BLURUSDT": 0.01995,
  "FIGHTUSDT": 0.006107,
  "ALTUSDT": 0.007374,
  "NOMUSDT": 0.003542,
  "CELOUSDT": 0.078,
  "GMXUSDT": 7.57,
  "REDUSDT": 0.1419,
  "KATUSDT": 0.01749,
  "ZEREBROUSDT": 0.007388,
  "YBUSDT": 0.1673,
  "ENJUSDT": 0.01915,
  "INUSDT": 0.06897,
  "ONTUSDT": 0.0433,
  "1000SATSUSDT": 1.19e-05,
  "ANKRUSDT": 0.004167,
  "SANTOSUSDT": 1.294,
  "AINUSDT": 0.03814,
  "WALUSDT": 0.07974,
  "UAIUSDT": 0.207,
  "EDENUSDT": 0.0333,
  "NEWTUSDT": 0.06697,
  "IOTXUSDT": 0.00512,
  "KOMAUSDT": 0.008038,
  "TRUTHUSDT": 0.009448,
  "ERAUSDT": 0.1423,
  "RSRUSDT": 0.001593,
  "SKLUSDT": 0.00682,
  "STBLUSDT": 0.03954,
  "TAKEUSDT": 0.01889,
  "POLYXUSDT": 0.0416,
  "GLMUSDT": 0.12959,
  "XPTUSDT": 2175.95,
  "QTUMUSDT": 0.926,
  "RAYSOLUSDT": 0.6107,
  "ZKCUSDT": 0.0829,
  "MELANIAUSDT": 0.1103,
  "1000CHEEMSUSDT": 0.0005642,
  "C98USDT": 0.0262,
  "ACHUSDT": 0.006898,
  "SONICUSDT": 0.0446,
  "CTSIUSDT": 0.0244,
  "HOLOUSDT": 0.05975,
  "DRIFTUSDT": 0.0861,
  "SAGAUSDT": 0.03234,
  "COOKIEUSDT": 0.02123,
  "WOOUSDT": 0.01821,
  "LSKUSDT": 0.1323,
  "DEGOUSDT": 0.3024,
  "MAGMAUSDT": 0.1496,
  "ARIAUSDT": 0.07337,
  "SOLVUSDT": 0.003735,
  "HEMIUSDT": 0.00822,
  "IDOLUSDT": 0.01782,
  "TUSDT": 0.006645,
  "LABUSDT": 0.1769,
  "CHRUSDT": 0.0179,
  "ARPAUSDT": 0.00978,
  "THEUSDT": 0.2665,
  "BROCCOLI714USDT": 0.01313,
  "PROMPTUSDT": 0.04398,
  "DYMUSDT": 0.03741,
  "STORJUSDT": 0.0944,
  "HEIUSDT": 0.0778,
  "BELUSDT": 0.0951,
  "RLCUSDT": 0.3698,
  "FLUIDUSDT": 2.233,
  "NOTUSDT": 0.0003746,
  "CROSSUSDT": 0.10058,
  "1MBABYDOGEUSDT": 0.0004045,
  "RVNUSDT": 0.00562,
  "HOTUSDT": 0.000391,
  "RDNTUSDT": 0.005587,
  "PROMUSDT": 1.114,
  "BIGTIMEUSDT": 0.0138,
  "XPDUSDT": 1703.1,
  "FRAXUSDT": 0.6114,
  "IDUSDT": 0.04241,
  "ICNTUSDT": 0.3344,
  "BBUSDT": 0.02727,
  "FIDAUSDT": 0.01582,
  "DOGSUSDT": 2.8e-05,
  "BANANAUSDT": 4.513,
  "LISTAUSDT": 0.0871,
  "ASTRUSDT": 0.007143,
  "METISUSDT": 3.319,
  "CVCUSDT": 0.03048,
  "ONEUSDT": 0.00237,
  "GRIFFAINUSDT": 0.00936,
  "DEEPUSDT": 0.02616,
  "AEVOUSDT": 0.02412,
  "GOATUSDT": 0.0186,
  "AMZNUSDT": 208.72,
  "MAVUSDT": 0.01384,
  "CUSDT": 0.04961,
  "SSVUSDT": 2.824,
  "BASUSDT": 0.006455,
  "SXTUSDT": 0.01846,
  "TREEUSDT": 0.06733,
  "AIUSDT": 0.02188,
  "RONINUSDT": 0.0983,
  "TRUUSDT": 0.005138,
  "ALLINDEXUSDT": 0.4725,
  "SYNUSDT": 0.05042,
  "CVXUSDT": 1.933,
  "VANRYUSDT": 0.005077,
  "NTRNUSDT": 0.01172,
  "HYPERUSDT": 0.0903,
  "COTIUSDT": 0.01206,
  "LQTYUSDT": 0.2923,
  "ICXUSDT": 0.0361,
  "HFTUSDT": 0.01451,
  "EVAAUSDT": 0.4456,
  "ALPINEUSDT": 0.4289,
  "HAEDALUSDT": 0.02721,
  "TACUSDT": 0.003901,
  "COINUSDT": 194.09,
  "XVSUSDT": 3.017,
  "APRUSDT": 0.0963,
  "EPICUSDT": 0.2791,
  "MEWUSDT": 0.0006223,
  "BANDUSDT": 0.2145,
  "DOLOUSDT": 0.03478,
  "HMSTRUSDT": 0.0001582,
  "ACXUSDT": 0.03488,
  "CKBUSDT": 0.001537,
  "BROCCOLIF3BUSDT": 0.00392,
  "SCRUSDT": 0.04457,
  "PLAYUSDT": 0.02024,
  "GUSDT": 0.003386,
  "GTCUSDT": 0.086,
  "BNTUSDT": 0.2969,
  "IRYSUSDT": 0.02006,
  "MOVRUSDT": 1.291,
  "VINEUSDT": 0.01731,
  "ONUSDT": 0.07338,
  "MITOUSDT": 0.03921,
  "VTHOUSDT": 0.000598,
  "TURTLEUSDT": 0.04307,
  "RAREUSDT": 0.01603,
  "ACEUSDT": 0.1511,
  "A2ZUSDT": 0.000841,
  "REZUSDT": 0.002897,
  "HOOKUSDT": 0.02284,
  "CARVUSDT": 0.06087,
  "NFPUSDT": 0.01517,
  "AIOTUSDT": 0.0224,
  "SHELLUSDT": 0.03005,
  "BRETTUSDT": 0.007908,
  "SPORTFUNUSDT": 0.04281,
  "FLOCKUSDT": 0.0576,
  "1000WHYUSDT": 1.14e-05,
  "IOSTUSDT": 0.001177,
  "BICOUSDT": 0.02065,
  "PHBUSDT": 0.1515,
  "ELSAUSDT": 0.07621,
  "WAXPUSDT": 0.006297,
  "RIFUSDT": 0.03291,
  "TLMUSDT": 0.001695,
  "MLNUSDT": 3.385,
  "ARKUSDT": 0.1757,
  "FUNUSDT": 0.001334,
  "SPELLUSDT": 0.0001735,
  "IRUSDT": 0.06103,
  "CETUSUSDT": 0.01688,
  "ILVUSDT": 3.658,
  "ATAUSDT": 0.0122,
  "ZETAUSDT": 0.05251,
  "CLANKERUSDT": 28.59,
  "XAIUSDT": 0.00975,
  "TOWNSUSDT": 0.003386,
  "PORTALUSDT": 0.0121,
  "DUSDT": 0.007134,
  "BMTUSDT": 0.01553,
  "BLESSUSDT": 0.004478,
  "TOSHIUSDT": 0.0002087,
  "VICUSDT": 0.0477,
  "USTCUSDT": 0.005237,
  "1000XECUSDT": 0.00708,
  "MTLUSDT": 0.2772,
  "AVAUSDT": 0.2047,
  "INTCUSDT": 43.52,
  "OGNUSDT": 0.0205,
  "PUNDIXUSDT": 0.1535,
  "FORTHUSDT": 0.981,
  "BDXNUSDT": 0.00842,
  "HIVEUSDT": 0.06396,
  "1000CATUSDT": 0.001768,
  "BOBUSDT": 0.006137,
  "ACUUSDT": 0.09462,
  "SAFEUSDT": 0.1055,
  "JCTUSDT": 0.001561,
  "HIGHUSDT": 0.1422,
  "CGPTUSDT": 0.02218,
  "DIAUSDT": 0.1848,
  "RLSUSDT": 0.004269,
  "PIXELUSDT": 0.005188,
  "ONGUSDT": 0.06326,
  "TRUSTUSDT": 0.0714,
  "FLUXUSDT": 0.05998,
  "RECALLUSDT": 0.04941,
  "POWRUSDT": 0.06353,
  "ORDERUSDT": 0.05427,
  "MOCAUSDT": 0.01526,
  "MBOXUSDT": 0.01885,
  "COSUSDT": 0.001042,
  "PLTRUSDT": 148.11,
  "SCRTUSDT": 0.0742,
  "CHILLGUYUSDT": 0.01073,
  "CELRUSDT": 0.00258,
  "INXUSDT": 0.011943,
  "LUMIAUSDT": 0.06354,
  "OXTUSDT": 0.01809,
  "JOEUSDT": 0.0409,
  "AERGOUSDT": 0.05495,
  "SYSUSDT": 0.01168,
  "DOODUSDT": 0.003144,
  "CTKUSDT": 0.1758,
  "SLPUSDT": 0.0005476,
  "USUSDT": 0.002861,
  "XANUSDT": 0.006772,
  "HOODUSDT": 79.18,
  "TAIKOUSDT": 0.1201,
  "PUFFERUSDT": 0.02865,
  "ETHWUSDT": 0.3236,
  "BRUSDT": 0.0564,
  "PUMPBTCUSDT": 0.01462,
  "SQDUSDT": 0.03548,
  "DODOXUSDT": 0.015228,
  "ZKJUSDT": 0.02391,
  "1000000BOBUSDT": 0.01271,
  "MAVIAUSDT": 0.03472,
  "B3USDT": 0.0003708,
  "1000000MOGUSDT": 0.163,
  "VFYUSDT": 0.01645,
  "DEGENUSDT": 0.0007239,
  "OLUSDT": 0.01315
}