{
  "BTCUSDT": 67189.5,
  "ETHUSDT": 1966.24,
  "ETH/USDCUSDT": 1944.93,
  "BTC/USDCUSDT": 66366.4,
  "SOLUSDT": 81.49,
  "XAGUSDT": 77.25,
  "BTC/USDUSDT": 67105.6,
  "XAUUSDT": 4982.95,
  "XRPUSDT": 1.4264,
  "PIPPINUSDT": 0.5094,
  "ETH/USDUSDT": 1965.85,
  "WLFIUSDT": 0.1204,
  "RIVERUSDT": 7.881,
  "DOGEUSDT": 0.09891,
  "ZECUSDT": 268.87,
  "BNBUSDT": 605.26,
  "ORCAUSDT": 1.255,
  "CYBERUSDT": 0.6608,
  "ESPUSDT": 0.09219,
  "HYPEUSDT": 28.703,
  "SOL/USDCUSDT": 81.46,
  "1000PEPEUSDT": 0.0042517,
  "NAORISUSDT": 0.04717,
  "SPACEUSDT": 0.011882,
  "SUIUSDT": 0.9328,
  "ADAUSDT": 0.2744,
  "PAXGUSDT": 4984.6,
  "AVAXUSDT": 8.89,
  "VVVUSDT": 3.772,
  "KITEUSDT": 0.21916,
  "XRP/USDCUSDT": 1.4255,
  "JTOUSDT": 0.3002,
  "LINKUSDT": 8.6,
  "BCHUSDT": 554.05,
  "ASTERUSDT": 0.7036,
  "PUMPUSDT": 0.002018,
  "TAOUSDT": 184.5,
  "AAVEUSDT": 122.94,
  "SIRENUSDT": 0.20997,
  "TRUMPUSDT": 3.384,
  "INITUSDT": 0.101,
  "GUNUSDT": 0.0286,
  "FILUSDT": 0.926,
  "LTCUSDT": 53.3,
  "SOL/USDUSDT": 80.68,
  "JELLYJELLYUSDT": 0.07218,
  "BERAUSDT": 0.6119,
  "STEEMUSDT": 0.05544,
  "UNIUSDT": 3.407,
  "GPSUSDT": 0.013845,
  "DOTUSDT": 1.313,
  "STABLEUSDT": 0.028188,
  "ATOMUSDT": 2.365,
  "ENSOUSDT": 1.1934,
  "OPUSDT": 0.1697,
  "NEARUSDT": 1.018,
  "WIFUSDT": 0.222,
  "WLDUSDT": 0.379,
  "ENAUSDT": 0.115,
  "CLOUSDT": 0.08508,
  "BNB/USDCUSDT": 605.63,
  "APTUSDT": 0.878,
  "POWERUSDT": 0.34298,
  "MYXUSDT": 1.051,
  "AXSUSDT": 1.296,
  "TRXUSDT": 0.27897,
  "XRP/USDUSDT": 1.4308,
  "RPLUSDT": 2.116,
  "PENGUUSDT": 0.006845,
  "FARTCOINUSDT": 0.1873,
  "1000SHIBUSDT": 0.006322,
  "ARBUSDT": 0.1076,
  "AWEUSDT": 0.10142,
  "BNB/USDUSDT": 607.59,
  "VIRTUALUSDT": 0.6185,
  "DOGE/USDCUSDT": 0.09886,
  "ZROUSDT": 1.5065,
  "ETH/BTCUSDT": 1945.471035,
  "ARCUSDT": 0.07929,
  "LITUSDT": 1.471,
  "HBARUSDT": 0.0993,
  "XMRUSDT": 329.81,
  "\u6211\u8e0f\u9a6c\u6765\u4e86USDT": 0.016316,
  "ROSEUSDT": 0.01356,
  "CRVUSDT": 0.244,
  "XLMUSDT": 0.16216,
  "DOGE/USDUSDT": 0.09885,
  "HUSDT": 0.16655,
  "DASHUSDT": 35.72,
  "SPXUSDT": 0.3344,
  "ZEC/USDCUSDT": 268.67,
  "SNXUSDT": 0.299,
  "ZAMAUSDT": 0.01898,
  "MONUSDT": 0.02016,
  "XPLUSDT": 0.0932,
  "TSLAUSDT": 410.32,
  "WLFI/USDCUSDT": 0.1202,
  "1000BONKUSDT": 0.006217,
  "ICPUSDT": 2.249,
  "LAUSDT": 0.2064,
  "POLUSDT": 0.10857,
  "\u5e01\u5b89\u4eba\u751fUSDT": 0.09206,
  "0GUSDT": 0.6275,
  "ETCUSDT": 8.451,
  "USELESSUSDT": 0.0429,
  "MUBARAKUSDT": 0.01766,
  "TONUSDT": 1.4161,
  "TRUTHUSDT": 0.00958,
  "SENTUSDT": 0.02254,
  "MORPHOUSDT": 1.4518,
  "BTRUSDT": 0.18302,
  "ONDOUSDT": 0.2659,
  "1000PEPE/USDCUSDT": 0.0042478,
  "TIAUSDT": 0.3288,
  "FOGOUSDT": 0.02493,
  "IPUSDT": 1.101,
  "SEIUSDT": 0.0726,
  "SUI/USDCUSDT": 0.9323,
  "JUPUSDT": 0.1529,
  "ONTUSDT": 0.0462,
  "TRIAUSDT": 0.01576,
  "RENDERUSDT": 1.417,
  "MUSDT": 1.4128,
  "AZTECUSDT": 0.01867,
  "PENDLEUSDT": 1.198,
  "ZORAUSDT": 0.02137,
  "MOODENGUSDT": 0.05717,
  "FETUSDT": 0.1654,
  "DUSKUSDT": 0.09732,
  "GALAUSDT": 0.00388,
  "INJUSDT": 2.983,
  "BANUSDT": 0.11819,
  "TAKEUSDT": 0.02327,
  "SONICUSDT": 0.04687,
  "BEATUSDT": 0.2024,
  "MERLUSDT": 0.05553,
  "SPORTFUNUSDT": 0.03664,
  "RAYSOLUSDT": 0.637,
  "DYDXUSDT": 0.101,
  "HOODUSDT": 75.1,
  "BIOUSDT": 0.02374,
  "OMUSDT": 0.05631,
  "ENSUSDT": 6.693,
  "COMPUSDT": 17.75,
  "LUNA2USDT": 0.06626,
  "XNYUSDT": 0.005636,
  "MOVEUSDT": 0.02398,
  "HUMAUSDT": 0.013842,
  "SANDUSDT": 0.08453,
  "MITOUSDT": 0.04473,
  "NEIROUSDT": 7.33e-05,
  "ACEUSDT": 0.1675,
  "FIGHTUSDT": 0.006508,
  "LDOUSDT": 0.3293,
  "ALGOUSDT": 0.091,
  "ALLOUSDT": 0.09524,
  "COLLECTUSDT": 0.07118,
  "MMTUSDT": 0.1324,
  "GASUSDT": 1.612,
  "BCH/USDCUSDT": 553.67,
  "BASUSDT": 0.006738,
  "ZILUSDT": 0.00402,
  "SKRUSDT": 0.019071,
  "CAKEUSDT": 1.2708,
  "CHZUSDT": 0.03935,
  "ADA/USDUSDT": 0.2744,
  "SKYUSDT": 0.06587,
  "FHEUSDT": 0.04098,
  "LYNUSDT": 0.26942,
  "CYSUSDT": 0.4952,
  "LINEAUSDT": 0.003541,
  "SUI/USDUSDT": 0.9321,
  "GIGGLEUSDT": 30.1,
  "ZENUSDT": 5.971,
  "MEUSDT": 0.1302,
  "EIGENUSDT": 0.1981,
  "EULUSDT": 0.901,
  "AVNTUSDT": 0.1907,
  "IRYSUSDT": 0.02537,
  "APEUSDT": 0.1171,
  "1000FLOKIUSDT": 0.03054,
  "VETUSDT": 0.007856,
  "PYTHUSDT": 0.0542,
  "ZKUSDT": 0.0207,
  "ZKPUSDT": 0.09102,
  "PLAYUSDT": 0.02061,
  "MAGICUSDT": 0.07085,
  "INTCUSDT": 45.48,
  "ETHFIUSDT": 0.4633,
  "ORDIUSDT": 2.659,
  "CRCLUSDT": 63.27,
  "ARIAUSDT": 0.07432,
  "CCUSDT": 0.16938,
  "BULLAUSDT": 0.0265,
  "SOMIUSDT": 0.1948,
  "ADA/USDCUSDT": 0.2743,
  "WETUSDT": 0.08417,
  "LINK/USDCUSDT": 8.596,
  "AUCTIONUSDT": 5.033,
  "LINK/USDUSDT": 8.594,
  "LIGHTUSDT": 0.2452,
  "C98USDT": 0.0283,
  "BIRBUSDT": 0.18646,
  "STGUSDT": 0.1308,
  "AVAX/USDCUSDT": 8.884,
  "CVXUSDT": 2.015,
  "1000LUNCUSDT": 0.03442,
  "STRKUSDT": 0.04622,
  "PTBUSDT": 0.001376,
  "FRAXUSDT": 0.648,
  "FIL/USDCUSDT": 0.925,
  "COINUSDT": 164.39,
  "PROMUSDT": 1.375,
  "XPTUSDT": 2084.97,
  "TRBUSDT": 14.912,
  "SYRUPUSDT": 0.23586,
  "OGUSDT": 3.268,
  "SUSDT": 0.04597,
  "ZKCUSDT": 0.0938,
  "BREVUSDT": 0.132,
  "BARDUSDT": 0.7588,
  "ARB/USDCUSDT": 0.1076,
  "KSMUSDT": 4.625,
  "UBUSDT": 0.04124,
  "AIAUSDT": 0.10025,
  "JASMYUSDT": 0.005706,
  "STXUSDT": 0.2539,
  "ANIMEUSDT": 0.005176,
  "PLTRUSDT": 135.22,
  "ARUSDT": 1.975,
  "TURBOUSDT": 0.0010521,
  "KASUSDT": 0.03115,
  "ENA/USDCUSDT": 0.115,
  "WCTUSDT": 0.06042,
  "SUPERUSDT": 0.1277,
  "ZBTUSDT": 0.07174,
  "ALTUSDT": 0.00825,
  "TRUMP/USDCUSDT": 3.383,
  "PNUTUSDT": 0.04798,
  "QNTUSDT": 68.08,
  "MSTRUSDT": 125.15,
  "WUSDT": 0.01979,
  "HIVEUSDT": 0.06866,
  "ATUSDT": 0.16081,
  "XPDUSDT": 1720.1,
  "RESOLVUSDT": 0.06023,
  "VELVETUSDT": 0.07056,
  "MANAUSDT": 0.0985,
  "NEAR/USDCUSDT": 1.017,
  "LTC/USDCUSDT": 53.27,
  "IOUSDT": 0.1103,
  "NIGHTUSDT": 0.0573,
  "IRUSDT": 0.08777,
  "RAVEUSDT": 0.38252,
  "ACHUSDT": 0.007481,
  "TRADOORUSDT": 1.414,
  "ARKMUSDT": 0.1125,
  "DOLOUSDT": 0.03628,
  "UMAUSDT": 0.4907,
  "POLYXUSDT": 0.04342,
  "TNSRUSDT": 0.05122,
  "LPTUSDT": 2.345,
  "LABUSDT": 0.15361,
  "GMTUSDT": 0.01209,
  "RUNEUSDT": 0.3973,
  "FFUSDT": 0.07966,
  "XTZUSDT": 0.386,
  "NOMUSDT": 0.005298,
  "LRCUSDT": 0.03296,
  "INUSDT": 0.0602,
  "MINAUSDT": 0.06471,
  "DRIFTUSDT": 0.0896,
  "METUSDT": 0.2084,
  "DEEPUSDT": 0.02833,
  "MIRAUSDT": 0.0912,
  "GWEIUSDT": 0.028101,
  "COWUSDT": 0.1965,
  "IMXUSDT": 0.1618,
  "TAIKOUSDT": 0.1307,
  "BOMEUSDT": 0.0004137,
  "BANANAS31USDT": 0.004519,
  "QUSDT": 0.02062,
  "BANKUSDT": 0.04176,
  "XVGUSDT": 0.00594,
  "PIEVERSEUSDT": 0.4031,
  "INXUSDT": 0.012383,
  "MELANIAUSDT": 0.1192,
  "AEROUSDT": 0.3051,
  "ACUUSDT": 0.10347,
  "ICNTUSDT": 0.3702,
  "SUSHIUSDT": 0.2049,
  "STORJUSDT": 0.099,
  "TOWNSUSDT": 0.003663,
  "MEMEUSDT": 0.0006787,
  "FUSDT": 0.006087,
  "FLOWUSDT": 0.03743,
  "2ZUSDT": 0.07402,
  "NILUSDT": 0.05381,
  "COAIUSDT": 0.3243,
  "GRTUSDT": 0.0268,
  "THETAUSDT": 0.1975,
  "AAVE/USDCUSDT": 122.85,
  "BCH/USDUSDT": 553.59,
  "AIXBTUSDT": 0.02027,
  "API3USDT": 0.306,
  "CKBUSDT": 0.001609,
  "AAVE/USDUSDT": 122.85,
  "TWTUSDT": 0.546,
  "CFXUSDT": 0.05217,
  "MASKUSDT": 0.4512,
  "WIF/USDCUSDT": 0.2218,
  "SAGAUSDT": 0.03234,
  "EGLDUSDT": 4.51,
  "CRV/USDCUSDT": 0.245,
  "LAYERUSDT": 0.0859,
  "HEMIUSDT": 0.01001,
  "ELSAUSDT": 0.07612,
  "SSVUSDT": 3.142,
  "KAITOUSDT": 0.3045,
  "ATOM/USDUSDT": 2.366,
  "RLSUSDT": 0.00541,
  "TREEUSDT": 0.07149,
  "POPCATUSDT": 0.05052,
  "AXLUSDT": 0.05739,
  "YFIUSDT": 2816.0,
  "AVAX/USDUSDT": 8.88,
  "CLANKERUSDT": 31.25,
  "LSKUSDT": 0.1434,
  "FIL/USDUSDT": 0.925,
  "PEOPLEUSDT": 0.0067,
  "REZUSDT": 0.003087,
  "ALICEUSDT": 0.107,
  "OGNUSDT": 0.0225,
  "XVSUSDT": 3.128,
  "PENGU/USDCUSDT": 0.006838,
  "NXPCUSDT": 0.2672,
  "NEOUSDT": 2.714,
  "1000SATSUSDT": 1.12e-05,
  "LTC/USDUSDT": 53.28,
  "PLUMEUSDT": 0.01041,
  "ZRXUSDT": 0.1066,
  "WIF/USDUSDT": 0.2218,
  "PARTIUSDT": 0.10394,
  "1INCHUSDT": 0.092,
  "IOTAUSDT": 0.0669,
  "QTUMUSDT": 0.951,
  "OPENUSDT": 0.1592,
  "GLMUSDT": 0.17659,
  "BATUSDT": 0.1229,
  "JSTUSDT": 0.042335,
  "BROCCOLI714USDT": 0.01375,
  "UNI/USDUSDT": 3.404,
  "KAIAUSDT": 0.05671,
  "ACTUSDT": 0.01465,
  "FOLKSUSDT": 1.285,
  "UAIUSDT": 0.2098,
  "AEVOUSDT": 0.02701,
  "HOMEUSDT": 0.027581,
  "LQTYUSDT": 0.2791,
  "ARPAUSDT": 0.0097,
  "METISUSDT": 3.549,
  "WOOUSDT": 0.01697,
  "VANAUSDT": 1.484,
  "CHRUSDT": 0.0233,
  "PROVEUSDT": 0.3125,
  "USTCUSDT": 0.005003,
  "BBUSDT": 0.02922,
  "KMNOUSDT": 0.02817,
  "COTIUSDT": 0.01174,
  "HAEDALUSDT": 0.02846,
  "MANTAUSDT": 0.0749,
  "USDCUSDT": 0.999897,
  "VANRYUSDT": 0.005696,
  "BOBUSDT": 0.006532,
  "SYNUSDT": 0.04773,
  "RSRUSDT": 0.001468,
  "IDUSDT": 0.04921,
  "TOSHIUSDT": 0.0002108,
  "AMZNUSDT": 204.92,
  "BLUAIUSDT": 0.005312,
  "ATHUSDT": 0.005701,
  "DYMUSDT": 0.044,
  "SWARMSUSDT": 0.00676,
  "1000RATSUSDT": 0.0483,
  "HOTUSDT": 0.000385,
  "TURTLEUSDT": 0.04321,
  "LISTAUSDT": 0.0881,
  "NMRUSDT": 8.133,
  "4USDT": 0.0091,
  "SPKUSDT": 0.02111,
  "SOPHUSDT": 0.009279,
  "BRETTUSDT": 0.00745,
  "SQDUSDT": 0.03936,
  "DOT/USDUSDT": 1.312,
  "OP/USDUSDT": 0.1697,
  "BTCDOMUSDT": 5062.6,
  "ERAUSDT": 0.1563,
  "SHELLUSDT": 0.03054,
  "UNI/USDCUSDT": 3.403,
  "WLD/USDCUSDT": 0.3786,
  "IP/USDCUSDT": 1.1,
  "FIDAUSDT": 0.01888,
  "SXTUSDT": 0.02099,
  "SCRTUSDT": 0.0881,
  "HANAUSDT": 0.03511,
  "NOTUSDT": 0.0003842,
  "SAPIENUSDT": 0.08344,
  "AUSDT": 0.0824,
  "EDUUSDT": 0.126,
  "SAHARAUSDT": 0.01549,
  "YGGUSDT": 0.03929,
  "CELOUSDT": 0.079,
  "WALUSDT": 0.0806,
  "ENJUSDT": 0.0204,
  "ANKRUSDT": 0.004452,
  "TIA/USDCUSDT": 0.3285,
  "FORMUSDT": 0.2151,
  "EPICUSDT": 0.2867,
  "FLOCKUSDT": 0.05943,
  "MAVUSDT": 0.01642,
  "SAFEUSDT": 0.1114,
  "RECALLUSDT": 0.0518,
  "DEGOUSDT": 0.3453,
  "ILVUSDT": 3.786,
  "XANUSDT": 0.00789,
  "ICXUSDT": 0.0393,
  "BANANAUSDT": 4.399,
  "ONEUSDT": 0.00247,
  "ONGUSDT": 0.06706,
  "BEAMXUSDT": 0.002284,
  "SKLUSDT": 0.00679,
  "XAIUSDT": 0.01005,
  "1MBABYDOGEUSDT": 0.0003847,
  "ALCHUSDT": 0.0817,
  "AKEUSDT": 0.0002553,
  "EDENUSDT": 0.03358,
  "YBUSDT": 0.1601,
  "HFTUSDT": 0.01728,
  "KERNELUSDT": 0.06447,
  "MAGMAUSDT": 0.09638,
  "HYPERUSDT": 0.0993,
  "GUAUSDT": 0.15021,
  "DAMUSDT": 0.01782,
  "HBAR/USDCUSDT": 0.09921,
  "ENS/USDUSDT": 6.667,
  "STBLUSDT": 0.03829,
  "ESPORTSUSDT": 0.3687,
  "DEXEUSDT": 2.257,
  "SOLVUSDT": 0.00455,
  "SUNUSDT": 0.01728,
  "BABYUSDT": 0.01374,
  "GMXUSDT": 6.37,
  "1000BONK/USDCUSDT": 0.006212,
  "TRUSTUSDT": 0.0769,
  "GTCUSDT": 0.095,
  "NEWTUSDT": 0.06987,
  "FUNUSDT": 0.001316,
  "GOATUSDT": 0.02228,
  "KAVAUSDT": 0.0523,
  "VICUSDT": 0.04931,
  "VINEUSDT": 0.01857,
  "TAGUSDT": 0.0003843,
  "RVNUSDT": 0.0061,
  "ASTRUSDT": 0.007526,
  "NEAR/USDUSDT": 1.017,
  "POWRUSDT": 0.06595,
  "HOLOUSDT": 0.05818,
  "SOONUSDT": 0.1689,
  "1000SHIB/USDCUSDT": 0.006317,
  "BSVUSDT": 16.39,
  "XPINUSDT": 0.001909,
  "JCTUSDT": 0.001771,
  "XLM/USDUSDT": 0.16203,
  "AIOTUSDT": 0.02916,
  "KGENUSDT": 0.16921,
  "COOKIEUSDT": 0.01826,
  "BIO/USDCUSDT": 0.02372,
  "AIOUSDT": 0.07393,
  "MOCAUSDT": 0.0163,
  "APT/USDUSDT": 0.876,
  "APRUSDT": 0.09083,
  "KNCUSDT": 0.1356,
  "DOGSUSDT": 2.79e-05,
  "BLURUSDT": 0.02046,
  "TRUUSDT": 0.006117,
  "TUSDT": 0.007131,
  "BLESSUSDT": 0.005159,
  "GRASSUSDT": 0.1879,
  "ZEREBROUSDT": 0.00768,
  "BANDUSDT": 0.231,
  "ACXUSDT": 0.03547,
  "FLUIDUSDT": 2.146,
  "RIFUSDT": 0.03265,
  "AGTUSDT": 0.004767,
  "USUSDT": 0.003768,
  "USUALUSDT": 0.01495,
  "TUTUSDT": 0.01111,
  "1000000MOGUSDT": 0.1696,
  "BIGTIMEUSDT": 0.01461,
  "DENTUSDT": 0.000139,
  "STOUSDT": 0.05348,
  "MEWUSDT": 0.0006068,
  "TRX/USDUSDT": 0.2788,
  "SCRUSDT": 0.04728,
  "AIUSDT": 0.02283,
  "1000CATUSDT": 0.00179,
  "SFPUSDT": 0.2651,
  "RAREUSDT": 0.01942,
  "RLCUSDT": 0.4198,
  "NTRNUSDT": 0.01377,
  "BUSDT": 0.1388,
  "BICOUSDT": 0.0225,
  "PHBUSDT": 0.1544,
  "BELUSDT": 0.095,
  "EVAAUSDT": 0.4748,
  "DUSDT": 0.00753,
  "ONUSDT": 0.09761,
  "GRIFFAINUSDT": 0.00917,
  "THEUSDT": 0.2656,
  "PIXELUSDT": 0.00529,
  "B2USDT": 0.7016,
  "TLMUSDT": 0.001668,
  "GUSDT": 0.003847,
  "KOMAUSDT": 0.00703,
  "ARKUSDT": 0.1882,
  "MTLUSDT": 0.2795,
  "IOTXUSDT": 0.00542,
  "HMSTRUSDT": 0.0001757,
  "CELRUSDT": 0.00262,
  "IOSTUSDT": 0.001232,
  "SIGNUSDT": 0.02651,
  "CHILLGUYUSDT": 0.0106,
  "TSTUSDT": 0.01047,
  "CTSIUSDT": 0.0252,
  "LUMIAUSDT": 0.06461,
  "HOOKUSDT": 0.0247,
  "BNTUSDT": 0.2816,
  "ORDERUSDT": 0.05739,
  "AGLDUSDT": 0.2187,
  "PORTALUSDT": 0.01404,
  "BRUSDT": 0.05054,
  "SPELLUSDT": 0.0001858,
  "ALPINEUSDT": 0.4388,
  "MAVIAUSDT": 0.03456,
  "AVAAIUSDT": 0.00748,
  "RDNTUSDT": 0.005635,
  "B3USDT": 0.0004298,
  "PNUT/USDCUSDT": 0.04797,
  "AKTUSDT": 0.3174,
  "BDXNUSDT": 0.01061,
  "DOODUSDT": 0.003525,
  "PHAUSDT": 0.02439,
  "IDOLUSDT": 0.02008,
  "1000XECUSDT": 0.00786,
  "SANTOSUSDT": 1.871,
  "ASRUSDT": 1.406,
  "CATIUSDT": 0.03947,
  "WAXPUSDT": 0.006754,
  "ETC/USDUSDT": 8.441,
  "CARVUSDT": 0.06278,
  "MEGAUSDT": 0.12665,
  "ATAUSDT": 0.0124,
  "NFPUSDT": 0.01659,
  "HIPPOUSDT": 0.000646,
  "PROMPTUSDT": 0.04543,
  "MOVRUSDT": 1.391,
  "CETUSUSDT": 0.01651,
  "A2ZUSDT": 0.000899,
  "DIAUSDT": 0.1933,
  "MLNUSDT": 3.549,
  "VELODROMEUSDT": 0.014,
  "FLUXUSDT": 0.0668,
  "RONINUSDT": 0.0962,
  "ZETAUSDT": 0.05192,
  "ORDI/USDCUSDT": 2.656,
  "CUSDT": 0.05556,
  "JOEUSDT": 0.03572,
  "REDUSDT": 0.1731,
  "VTHOUSDT": 0.0005971,
  "1000WHYUSDT": 1.16e-05,
  "MBOXUSDT": 0.01995,
  "ETHFI/USDCUSDT": 0.4627,
  "HEIUSDT": 0.0838,
  "1000CHEEMSUSDT": 0.0004693,
  "CGPTUSDT": 0.02119,
  "CROSSUSDT": 0.10745,
  "SLPUSDT": 0.0006352,
  "HIGHUSDT": 0.1447,
  "CVCUSDT": 0.03328,
  "BOME/USDCUSDT": 0.0004133,
  "ETHWUSDT": 0.3201,
  "WLD/USDUSDT": 0.3786,
  "ZKJUSDT": 0.02338,
  "PUMPBTCUSDT": 0.01663,
  "TAUSDT": 0.03592,
  "AINUSDT": 0.03342,
  "OXTUSDT": 0.01739,
  "DEGENUSDT": 0.00069,
  "VFYUSDT": 0.01779,
  "NEO/USDCUSDT": 2.713,
  "PUFFERUSDT": 0.03204,
  "ALGO/USDUSDT": 0.0909,
  "BMTUSDT": 0.01659,
  "FIOUSDT": 0.00891,
  "SYSUSDT": 0.01288,
  "KAITO/USDCUSDT": 0.3042,
  "PUNDIXUSDT": 0.1629,
  "AVAUSDT": 0.2081,
  "SKYAIUSDT": 0.03648,
  "1000000BOBUSDT": 0.01299,
  "AERGOUSDT": 0.05563,
  "DODOXUSDT": 0.015121,
  "OLUSDT": 0.01166,
  "ALLINDEXUSDT": 0.4739,
  "COSUSDT": 0.001053,
  "BROCCOLIF3BUSDT": 0.003673,
  "FORTHUSDT": 1.063,
  "SAND/USDUSDT": 0.0844,
  "TACUSDT": 0.004017,
  "CTKUSDT": 0.2065
}